{
  "keyword": "metabolism of drugs",
  "title": "Metabolism Of Drugs",
  "content": " *Disclosure: This article contains affiliate links. If you choose to purchase through these links, we may earn a commission at no additional cost to you. This helps us continue providing free health information.*\n\n# A Day in the Life: Understanding the Metabolism of Drugs\n\nMetabolism is a fundamental process that affects the way our bodies function, from processing the food we eat to breaking down the medications we take. In this day-in-the-life narrative, we'll explore how the metabolism of drugs works and why it's essential to our health and wellness.\n\n## Morning (7:00 AM - 12:00 PM)\n\n**7:00 AM:** As you wake up and start your day, your body is already at work metabolizing any medications you may have taken before bed. This process begins in the liver, where enzymes break down the drug into smaller molecules, called metabolites. This is the first step in the metabolism of drugs, known as phase I metabolism. During this phase, enzymes like cytochrome P450 modify the drug's chemical structure, making it easier for your body to eliminate.\n\n**8:00 AM:** You take your morning medications with a glass of water. As the drugs enter your system, they're absorbed into your bloodstream and circulated throughout your body. In some cases, the drug may be immediately effective. However, most drugs require metabolism before they can exert their intended effects.\n\n**9:00 AM:** Once the drug reaches the liver, phase I metabolism begins. This process can take anywhere from a few minutes to several hours, depending on the drug and your individual metabolic rate.\n\n## Midday (12:00 PM - 4:00 PM)\n\n**12:00 PM:** After a busy morning, you take a lunch break and enjoy a nutritious meal. As you eat, your body continues to metabolize the drugs you've taken. During this time, phase II metabolism occurs. In this phase, enzymes like UDP-glucuronosyltransferase (UGT) add a molecule, such as glucuronic acid, to the drug or its metabolites. This process, known as conjugation, makes the drug even more water-soluble, allowing it to be easily excreted from your body.\n\n**1:00 PM:** Now it's time to get back to work. As you concentrate on your tasks, your body continues to metabolize the drugs you've taken. The metabolites produced during phase I and phase II metabolism are then eliminated from your body through your urine, bile, or feces.\n\n## Afternoon (4:00 PM - 8:00 PM)\n\n**4:00 PM:** As the afternoon wears on, you may start to feel the effects of your medications wearing off. This is because the metabolites produced during the metabolism of drugs are often less potent than the original drug. In some cases, your healthcare provider may adjust your dosage or prescribe a different medication to ensure that you're receiving the appropriate amount of therapy.\n\n**6:00 PM:** You take your evening medications, which will continue to be metabolized throughout the night.\n\n## Evening (8:00 PM - 12:00 AM)\n\n**8:00 PM:** As you wind down for the day, it's essential to remember that the metabolism of drugs can be affected by various factors. These factors include your age, weight, liver and kidney function, genetics, and the presence of other medications or supplements in your system.\n\n**10:00 PM:** As you prepare for bed, it's crucial to follow your healthcare provider's instructions regarding your medications. Taking your medications as prescribed, at the right time, and in the correct dosage will help ensure that they're metabolized effectively and safely.\n\n## Night (12:00 AM - 7:00 AM)\n\n**12:00 AM:** As you sleep, your body continues to metabolize the medications you've taken. This process doesn't stop just because you're asleep.\n\n**6:00 AM:** As you wake up and start your day, your body is ready to metabolize any new medications you may need to take.\n\n---\n\nThe metabolism of drugs is a complex process that plays a vital role in our health and wellness. While medications can be lifesaving, it's essential to understand how they're metabolized and the factors that can affect their metabolism. By following your healthcare provider's instructions and being aware of the potential factors that can influence drug metabolism, you can help ensure that you're receiving the appropriate therapy and avoiding potential adverse effects.\n\nIf you're looking for additional support in maintaining a healthy metabolism, consider exploring [click here](https://0a72eyrjwisxgl36mgow4lrudn.hop.clickbank.net) to learn more about Java Burn, a metabolism booster for weight management.\n\n*Disclaimer: Always consult with your healthcare provider before starting any new supplement or medication.*",
  "format": "Day-in-the-Life",
  "word_count": 731,
  "products_mentioned": [
    "Java Burn"
  ],
  "generated_at": "2025-10-18T13:19:58.595618",
  "api_used": "together",
  "version": "v2_12_formats"
}