{
  "keyword": "depression brain scan",
  "title": "Depression Brain Scan",
  "content": " *Disclosure: This article contains affiliate links. If you choose to purchase through these links, we may earn a commission at no additional cost to you. This helps us continue providing free health information.*\n\n## Depression Brain Scans: A Comprehensive How-To Guide\n\nDepression is a prevalent mental health disorder that affects millions of people worldwide. While traditional methods of diagnosing depression rely on self-reported symptoms and clinical interviews, recent advances in neuroimaging technology have made it possible to visualize and measure brain activity associated with depression. This guide will walk you through the process of understanding depression brain scans, what you need for the procedure, and how to interpret the results.\n\nMany people find additional support helpful. [Click here to learn more about Pineal XT](https://hop.clickbank.net/?affiliate=dlking11&vendor=pxtvip&cbpage=tsl&affop=1), a supplement that supports pineal gland function and cognitive health.\n\nMany people find additional support helpful. [Click here to learn more about NeuroQuiet](https://hop.clickbank.net/?affiliate=dlking11&vendor=neuroquiet&cbpage=tsl&affop=1), a comprehensive formula that supports brain health and hearing function.\n\n",
  "format": "How-To Guide",
  "word_count": 110,
  "products_mentioned": [
    "Pineal XT",
    "NeuroQuiet"
  ],
  "generated_at": "2025-10-18T14:52:56.320169",
  "api_used": "together",
  "version": "v2_12_formats"
}