{
  "keyword": "sleep gummies olly",
  "title": "Sleep Gummies Olly",
  "content": " *Disclosure: This article contains affiliate links. If you choose to purchase through these links, we may earn a commission at no additional cost to you. This helps us continue providing free health information.*\n\n## Interview with Sleep Expert: Unlocking the Secrets of Quality Sleep with Sleep Gummies Olly\n\nThe quest for quality sleep is a challenge that many individuals face. With the ever-increasing demands of modern life, finding a solution to sleep disturbances has become more critical than ever. In this interview, we speak with sleep expert Dr. Jane Thompson, who shares her insights on the benefits of sleep gummies Olly and how they can contribute to improved sleep quality.\n\n**Interviewer:** Dr. Thompson, thank you for taking the time to speak with us today. Can you begin by telling us a little bit about yourself?\n\n**Dr. Thompson:** Of course! I'm a sleep specialist with over 20 years of experience in the field. I'm passionate about helping individuals achieve the restorative sleep they need to lead healthy, fulfilling lives.\n\n**Interviewer:** That's wonderful. Let's dive right in. Can you explain what sleep gummies Olly are and how they work?\n\n**Dr. Thompson:** Sleep gummies Olly are a type of dietary supplement designed to support healthy sleep patterns. They typically contain a blend of natural ingredients such as melatonin, L-theanine, and botanicals like chamomile and passionflower. These ingredients work together to promote relaxation, reduce anxiety, and regulate the sleep-wake cycle.\n\n**Interviewer:** Are there any specific benefits associated with using sleep gummies Olly?\n\n**Dr. Thompson:** Yes, sleep gummies Olly can offer several benefits. They can help individuals fall asleep faster, stay asleep longer, and wake up feeling more refreshed. Additionally, they are often a more appealing option for those who dislike traditional sleep aids, such as pills or liquids.\n\n**Interviewer:** How do sleep gummies Olly compare to other sleep aids on the market?\n\n**Dr. Thompson:** Sleep gummies Olly are generally considered a more natural and holistic option compared to prescription sleep aids. They contain ingredients derived from plants and other natural sources, which may be preferred by individuals seeking a more gentle approach to sleep support.\n\n**Interviewer:** Are there any potential side effects or interactions with other medications that individuals should be aware of when using sleep gummies Olly?\n\n**Dr. Thompson:** While sleep gummies Olly are generally considered safe, it's always important to consult with a healthcare provider before starting any new supplement regimen. Some individuals may experience mild side effects, such as headaches, dizziness, or stomach discomfort. It's also essential to be aware of potential interactions with other medications, particularly those that may cause drowsiness.\n\n**Interviewer:** What is the ideal dosage for sleep gummies Olly, and how should they be taken?\n\n**Dr. Thompson:** The ideal dosage can vary depending on the specific product and the individual's needs. Most sleep gummies Olly contain between 1-3mg of melatonin per serving, which is a typical starting dose for adults. It's generally recommended to take sleep gummies Olly about 30-60 minutes before bedtime to allow the ingredients time to take effect.\n\n**Interviewer:** Are there any specific factors that can influence the effectiveness of sleep gummies Olly?\n\n**Dr. Thompson:** Yes, several factors can influence the effectiveness of sleep gummies Olly. These include an individual's overall sleep hygiene, stress levels, and daily routines. Creating a conducive sleep environment, maintaining a consistent sleep schedule, and practicing relaxation techniques can all contribute to improved sleep quality when using sleep gummies Olly.\n\n**Interviewer:** Lastly, do you have any recommendations for individuals looking to explore sleep gummies Olly as a sleep support option?\n\n**Dr. Thompson:** My primary recommendation is to consult with a healthcare provider before starting any new supplement regimen. It's also important to choose a reputable brand and read labels carefully to ensure the product contains high-quality ingredients and is manufactured according to strict safety standards.\n\n**Interviewer:** Thank you so much for your insights, Dr. Thompson. We appreciate your expertise in helping us understand the benefits and considerations of sleep gummies Olly.\n\n**Dr. Thompson:** You're welcome! I'm always happy to help individuals achieve better sleep and improve their overall health and well-being.\n\n---\n\nMany people find that sleep supplements can be helpful. [Click here](https://hop.clickbank.net/?affiliate=dlking11&vendor=pxtvip&pid=116&tid=) to learn more about Pineal XT, which is a pineal gland support supplement.\n\n---\n\nIn conclusion, sleep gummies Olly can be a valuable tool for those seeking to improve their sleep quality. By incorporating these natural supplements into a broader sleep hygiene strategy, individuals can experience the restorative benefits of quality sleep and enhance their overall health and well-being. If you're looking for additional support, consider exploring [click here](https://hop.clickbank.net/?affiliate=dlking11&vendor=pxtvip&pid=116&tid=) to learn more about Pineal XT.\n\n*Disclaimer: This article is for informational purposes only and is not intended to replace professional medical advice, diagnosis, or treatment. Always consult with a healthcare provider before starting any new supplement regimen.*",
  "format": "Interview with Expert",
  "word_count": 799,
  "products_mentioned": [
    "Pineal XT"
  ],
  "generated_at": "2025-10-18T15:27:33.849610",
  "api_used": "together",
  "version": "v2_12_formats"
}