{
  "keyword": "inflammation pcos",
  "title": "Inflammation Pcos",
  "content": " ## The Connection Between Inflammation and PCOS: A Comprehensive FAQ\n\nPolycystic Ovary Syndrome (PCOS) is a common hormonal disorder affecting women of reproductive age. Characterized by irregular periods, high levels of androgens (male hormones), and cysts in the ovaries, PCOS can lead to a variety of health issues, including infertility, insulin resistance, and weight gain. One lesser-known aspect of PCOS is its link to chronic inflammation. In this article, we'll explore the connection between inflammation and PCOS, answering some of the most frequently asked questions on the topic.\n\nMany people find additional support helpful. [Click here to learn more about Flexafen](https://9c5143s6riwubw8dm7yyhdokdr.hop.clickbank.net), a powerful joint pain relief formula that reduces inflammation.\n\nMany people find additional support helpful. [Click here to learn more about Arctic Blast](https://1993eap6mdvsfw4303walxdpda.hop.clickbank.net), a fast-acting pain relief formula for chronic pain and inflammation.\n\n",
  "format": "FAQ Style",
  "word_count": 88,
  "products_mentioned": [
    "Ikaria Lean Belly Juice",
    "Flexafen",
    "Arctic Blast",
    "Java Burn"
  ],
  "generated_at": "2025-10-17T14:01:25.519366",
  "api_used": "together"
}