{
  "keyword": "how to cholesterol control naturally",
  "title": "How To Cholesterol Control Naturally",
  "content": " *Disclosure: This article contains affiliate links. If you choose to purchase through these links, we may earn a commission at no additional cost to you. This helps us continue providing free health information.*\n\n## How to Control Cholesterol Naturally: A Comprehensive Guide\n\nHigh cholesterol is a prevalent health issue that affects millions of people worldwide. If left unmanaged, it can lead to serious health complications such as heart disease and stroke. While medication is often necessary to control cholesterol levels, there are also several natural methods that can help. In this comprehensive guide, we will explore the various ways to control cholesterol naturally.\n\n### Background\n\nCholesterol is a waxy substance found in your blood. Your body needs cholesterol to build healthy cells, but high levels of cholesterol can increase your risk of heart disease. There are two types of cholesterol: low-density lipoprotein (LDL), or \"bad\" cholesterol, and high-density lipoprotein (HDL), or \"good\" cholesterol.\n\nSeveral factors can contribute to high cholesterol levels, including genetics, diet, lack of exercise, and smoking. While some risk factors, such as genetics, cannot be changed, others can be managed through lifestyle modifications.\n\n### 1. Diet\n\nEating a healthy diet is one of the most effective ways to control cholesterol levels naturally. Foods that are high in saturated and trans fats can increase LDL cholesterol levels, while foods that are high in fiber and unsaturated fats can help lower cholesterol levels. Here are some dietary changes you can make to help control your cholesterol levels:\n\n- Limit saturated fats: Saturated fats are found in animal products such as meat, dairy, and eggs. Try to limit your intake of these foods and choose leaner cuts of meat when possible.\n- Eliminate trans fats: Trans fats are often found in processed foods such as baked goods, fried foods, and snack foods. Check food labels carefully and avoid products that contain trans fats.\n- Eat more fiber: Foods that are high in fiber, such as fruits, vegetables, whole grains, and legumes, can help lower cholesterol levels. Aim for at least 25-30 grams of fiber per day.\n- Choose unsaturated fats: Unsaturated fats, such as those found in olive oil, avocados, and nuts, can help lower LDL cholesterol levels and increase HDL cholesterol levels.\n\n### 2. Exercise\n\nRegular exercise can help lower LDL cholesterol levels and increase HDL cholesterol levels. Aim for at least 30 minutes of moderate-intensity exercise, such as brisk walking, cycling, or swimming, on most days of the week. If you are new to exercise, start slowly and gradually increase your intensity and duration.\n\n### 3. Weight Management\n\nBeing overweight or obese can increase your risk of high cholesterol levels. Losing even a small amount of weight can help lower your cholesterol levels and improve your overall health. Aim for a healthy body mass index (BMI) of 18.5-24.9.\n\n### 4. Smoking Cessation\n\nSmoking can damage the walls of your arteries, leading to a buildup of cholesterol and plaque. Quitting smoking can help lower your cholesterol levels and reduce your risk of heart disease. If you are a smoker, talk to your healthcare provider about ways to quit.\n\n### 5. Stress Management\n\nStress can increase your cholesterol levels and contribute to unhealthy lifestyle habits, such as overeating and smoking. Finding healthy ways to manage stress, such as through meditation, yoga, or exercise, can help lower your cholesterol levels and improve your overall health.\n\n### 6. Supplements\n\nMany people find that supplements can be helpful in controlling cholesterol levels naturally. One such supplement is NeuroQuiet, a brain health and tinnitus relief supplement that contains a blend of natural ingredients, including red yeast rice, artichoke leaf extract, and CoQ10. These ingredients have been shown to help lower cholesterol levels and support overall brain health. [Click here](https://a851ey-huapohuajrpvm2bj0lq.hop.clickbank.net) to learn more about NeuroQuiet.\n\n### Conclusion\n\nControlling cholesterol levels naturally is an important part of maintaining overall health and reducing your risk of heart disease. By making dietary changes, incorporating regular exercise, managing your weight, quitting smoking, managing stress, and exploring natural supplements like NeuroQuiet, you can take control of your cholesterol levels and improve your overall health.\n\nRemember, it's important to talk to your healthcare provider before starting any new supplement regimen. They can help you determine if a supplement is right for you and ensure that it won't interact with any medications you may be taking.\n\nIf you're looking for additional support, consider exploring [click here](https://a851ey-huapohuajrpvm2bj0lq.hop.clickbank.net) to learn more about NeuroQuiet. With its natural blend of ingredients and commitment to promoting overall brain health, NeuroQuiet may be a valuable addition to your cholesterol control strategy.",
  "format": "Complete Guide",
  "word_count": 763,
  "products_mentioned": [
    "NeuroQuiet"
  ],
  "generated_at": "2025-10-18T15:28:28.635748",
  "api_used": "together",
  "version": "v2_12_formats"
}