{
  "id": 353,
  "keyword": "mental health unit near me",
  "title": "Boost Your Mental Health Unit Near Me",
  "slug": "mental-health-unit-near-me",
  "content": "# Boost Your Mental Health Unit Near Me\n\nTaking the courageous step to seek support for your mental well-being is a profound act of self-care. In moments of distress, confusion, or overwhelming challenge, knowing where to turn can make all the difference. This article is designed to be a comprehensive guide for anyone exploring the option of a mental health unit, often referred to as a psychiatric unit, behavioral health unit, or mental health facility, in their local area.\n\nYou'll gain a clear understanding of what these units offer, how they differ, and why they might be the right choice for your specific needs or those of a loved loved one. We will demystify the process of finding and accessing these vital resources, providing practical tips to navigate the complexities of mental healthcare. By the end of this read, you will feel more informed and empowered to make decisions about your mental health journey, armed with knowledge on how to identify quality care, prepare for treatment, and avoid common pitfalls. This guide aims to equip you with the insights necessary to connect with the professional support that can lead to stabilization, recovery, and a renewed sense of well-being.\n\n## Key Benefits of Seeking Support from a Mental Health Unit\n\nMental health units provide a structured and supportive environment designed to address a wide range of mental health conditions. Their benefits extend beyond immediate crisis intervention, offering a pathway to sustained recovery and improved quality of life.\n\n*   **Specialized and Intensive Care:** These units offer a level of care that often cannot be replicated in outpatient settings. Patients receive round-the-clock monitoring and access to a multidisciplinary team of professionals, including psychiatrists, psychologists, nurses, social workers, and therapists. This intensive approach allows for rapid stabilization during acute crises and comprehensive treatment planning tailored to individual needs.\n*   **Crisis Stabilization:** For individuals experiencing severe symptoms, such as acute psychosis, suicidal ideation, or profound depression, a mental health unit provides a safe and controlled environment. The immediate goal is to stabilize the individual, reduce acute distress, and ensure their safety, as well as the safety of others. This level of intervention is crucial in preventing further harm and initiating the recovery process.\n*   **Structured Therapeutic Environment:** Patients benefit from a structured daily schedule that often includes individual therapy, group therapy, psychoeducation, and recreational activities. This routine helps to re-establish a sense of normalcy, teach coping mechanisms, and build essential life skills in a supportive setting. Group therapy, in particular, fosters a sense of community and reduces feelings of isolation.\n*   **Comprehensive Assessment and Diagnosis:** Upon admission, individuals undergo a thorough psychiatric and medical evaluation. This comprehensive assessment helps in accurately diagnosing underlying conditions, identifying co-occurring disorders, and developing an effective, personalized treatment plan. Correct diagnosis is fundamental to effective intervention.\n*   **Medication Management and Monitoring:** For many mental health conditions, medication plays a crucial role. In a mental health unit, medication can be initiated, adjusted, and closely monitored by psychiatric professionals. This controlled environment allows for careful observation of efficacy and side effects, optimizing treatment outcomes more safely than in an outpatient setting.\n*   **Development of Coping Strategies and Skills:** Beyond immediate symptom management, units focus on equipping individuals with long-term coping strategies. Patients learn about their condition, identify triggers, develop relapse prevention plans, and acquire practical skills for managing stress, emotions, and interpersonal relationships. This empowers them to navigate challenges more effectively upon discharge.\n*   **Post-Discharge Planning and Aftercare:** A critical component of treatment in a mental health unit is comprehensive discharge planning. This involves arranging follow-up appointments with therapists and psychiatrists, connecting patients with community resources, and sometimes facilitating transitions to partial hospitalization programs or intensive outpatient programs. This ensures a continuum of care and supports sustained recovery.\n\n## Practical Tips to Get Started\n\nNavigating the process of finding and accessing a mental health unit can feel overwhelming. These practical tips are designed to guide you through each step, from understanding your options to preparing for treatment.\n\n### Understanding Different Types of Units\n\nMental health units come in various forms, each designed to meet different levels of need. Knowing the distinctions can help you identify the most appropriate care.\n\n*   **Inpatient Units:** These facilities provide 24/7 supervision and intensive care for individuals in acute crisis or those who require constant monitoring. Stays are typically short-term, focusing on stabilization and safety. They are ideal for severe symptoms like psychosis, severe depression with suicidal ideation, or acute substance withdrawal requiring medical management.\n*   **Outpatient Programs (Partial Hospitalization Programs - PHPs and Intensive Outpatient Programs - IOPs):** These programs offer structured therapy during the day or several days a week, allowing patients to return home in the evenings. PHPs are more intensive than IOPs, often running for most of the day, five days a week. IOPs typically involve fewer hours per day and fewer days per week. They are suitable for individuals who are stable enough not to require 24/7 care but still need significant therapeutic support.\n*   **Specialized Units:** Some units focus on specific conditions, such as addiction recovery, eating disorders, trauma, or geriatric mental health. If your needs fall into one of these categories, a specialized unit might offer more tailored and effective treatment approaches.\n\n### How to Begin Your Search\n\nFinding the right mental health unit often starts with leveraging trusted resources and conducting thorough research.\n\n*   **Consult Your Primary Care Physician (PCP):** Your PCP is an excellent first point of contact. They can assess your situation, offer initial guidance, and provide referrals to mental health specialists or facilities they trust. They often have established networks and can help navigate insurance requirements.\n*   **Reach Out to Mental Health Professionals:** If you already have a therapist or psychiatrist, they can offer invaluable guidance. They understand your history and can recommend units that align with your specific treatment needs and preferences.\n*   **Utilize Online Directories and Search Engines:** A simple search for \"mental health unit near me\" or \"psychiatric hospital near me\" can yield local results. Websites of national mental health organizations often provide searchable databases of accredited facilities. Be sure to look for reputable sources.\n*   **Contact Your Insurance Provider:** Your insurance company can provide a list of in-network facilities and explain your coverage for mental health services. Understanding your benefits upfront can save significant time and stress.\n*   **Explore Community Mental Health Centers:** Many communities offer mental health services, including crisis intervention and referrals to higher levels of care. These centers often serve as a gateway to various support systems, especially for those with limited resources.\n\n### What to Look For in a Unit\n\nOnce you have a list of potential units, it's crucial to evaluate them to ensure they meet high standards of care and align with your values.\n\n*   **Accreditation and Licensing:** Ensure the unit is accredited by recognized bodies (e.g., The Joint Commission) and licensed by the state. This indicates adherence to specific quality and safety standards.\n*   **Treatment Philosophy and Modalities:** Inquire about their approach to treatment. Do they offer evidence-based therapies like Cognitive Behavioral Therapy (CBT), Dialectical Behavior Therapy (DBT), or Eye Movement Desensitization and Reprocessing (EMDR)? Does their philosophy resonate with your beliefs about healing?\n*   **Staff Qualifications and Ratios:** Ask about the qualifications of the clinical staff (e.g., board-certified psychiatrists, licensed therapists). A healthy patient-to-staff ratio suggests more personalized attention.\n*   **Patient-Centered Care:** Look for units that emphasize individualized treatment plans, involve patients in decision-making, and respect patient autonomy and dignity.\n*   **Family Involvement:** Understand their policies on family visitation and involvement in the treatment process. Family support can be a crucial component of recovery.\n*   **Aftercare Planning:** A good unit will have a robust discharge planning process, ensuring a smooth transition back into daily life with appropriate follow-up care and community resources.\n\n### Preparing for Your First Contact\n\nBefore you make that initial call or visit, gathering some information and preparing questions can make the process smoother and more productive.\n\n*   **List of Questions:** Prepare a list of questions about the unit's programs, cost, insurance acceptance, visiting hours, typical length of stay, and aftercare options.\n*   **Medical and Mental Health History:** Have your medical history, current medications, and a brief overview of your mental health journey readily available. This will help the intake team assess your needs quickly.\n*   **Insurance Information:** Have your insurance card and policy details handy.\n*   **Support System:** Consider bringing a trusted family member or friend with you to appointments or on calls. They can offer emotional support, help remember information, and advocate on your behalf.\n\n### Navigating Insurance and Costs\n\nUnderstanding the financial aspects of mental health treatment is a key part of the planning process.\n\n*   **Understand Your Coverage:** Contact your insurance provider to understand your specific mental health benefits. Inquire about deductibles, co-pays, out-of-pocket maximums, and any pre-authorization requirements for inpatient or intensive outpatient care.\n*   **Out-of-Pocket Expenses:** Be prepared for potential out-of-pocket costs, even with insurance. Discuss these with the unit's admissions or financial office upfront.\n*   **Financial Assistance Programs:** Many hospitals and facilities offer financial assistance programs, sliding scale fees, or payment plans for eligible individuals. Don't hesitate to ask about these options.\n*   **Advocacy:** If you encounter difficulties with insurance coverage, consider seeking assistance from a patient advocate or a mental health advocacy organization.\n\n### Self-Care and Complementary Supports\n\nWhile professional treatment is paramount, integrating self-care and complementary supports can significantly enhance the recovery journey. These personal strategies can support overall well-being and complement the structured care received in a mental health unit. This might include practices like mindfulness, regular exercise, maintaining a balanced diet, and ensuring adequate sleep. Many people find that **cognitive support supplements** can be helpful. [Click here](https://a851ey-huapohuajrpvm2bj0lq.hop.clickbank.net) to learn more about **NeuroQuiet**, a supplement formulated to support brain health and hearing wellness. Always discuss any supplements with your healthcare provider to ensure they are appropriate for your individual health plan.\n\n## Common Mistakes to Avoid\n\nSeeking mental health support is a significant step, and being aware of common pitfalls can help ensure a smoother and more effective journey.\n\n*   **Delaying Seeking Help:** One of the most common mistakes is waiting until a crisis point before seeking help. Early intervention often leads to better outcomes and can prevent symptoms from escalating. If you recognize warning signs, act promptly.\n*   **Not Asking Enough Questions:** Don't be afraid to ask detailed questions about treatment plans, staff credentials, facility policies, and aftercare. The more informed you are, the better equipped you'll be to make the right decision for your care.\n*   **Focusing Solely on Cost Over Quality",
  "format": "Benefits & Tips",
  "word_count": 1763,
  "products_mentioned": [
    "NeuroQuiet"
  ],
  "generated_at": "2025-10-15T21:50:05.691856"
}