{
  "id": 395,
  "keyword": "stress vs strain graph",
  "title": "A Complete Guide to Stress Vs Strain Graph",
  "slug": "stress-vs-strain-graph",
  "content": "# A Complete Guide to Stress Vs Strain Graph\n\nHave you ever wondered why a bridge doesn't collapse under heavy loads, or how an airplane wing can withstand immense forces during flight? The secret lies in understanding how materials behave when subjected to external pressures. Engineers and scientists rely on a fundamental tool called the **stress-strain graph** to unlock these secrets. This powerful visual representation provides a comprehensive blueprint of a material's mechanical properties, illustrating its strength, stiffness, ductility, and resilience.\n\nWhether you're a student embarking on a journey into materials science, an engineer designing the next generation of structures, or simply curious about the physical world around you, grasping the concepts behind the stress-strain graph is invaluable. It\u2019s not just a theoretical curve; it\u2019s a practical roadmap that guides critical decisions in material selection, product design, and safety analysis. This article will demystify this essential graph, answering common questions and providing a clear, educational overview of its components and significance. Prepare to gain a deeper appreciation for the hidden strengths and vulnerabilities of the materials that shape our world.\n\n## Quick Overview\n\nThe stress-strain graph is a graphical representation of a material's response to an applied load. It plots **stress** on the y-axis against **strain** on the x-axis. At its core, **stress** quantifies the internal forces that particles within a material exert on each other as a result of an external force, normalized by the cross-sectional area over which the force is applied. It's essentially the intensity of internal forces. **Strain**, on the other hand, measures the deformation of the material relative to its original dimensions, indicating how much the material has stretched, compressed, or twisted. It's a dimensionless quantity, representing the fractional change in length or shape.\n\nWhen a material is subjected to a gradually increasing load, it deforms. The stress-strain graph meticulously records this deformation behavior. Initially, many materials exhibit an **elastic region**, where deformation is temporary and reversible; remove the load, and the material returns to its original shape. Beyond a certain point, known as the **yield point**, the material enters the **plastic region**, where deformation becomes permanent. Further loading can lead to a peak known as the **ultimate tensile strength**, after which the material begins to \"neck\" (localize deformation) and eventually **fractures**. This graph is crucial for characterizing material properties like stiffness (Modulus of Elasticity), yield strength, tensile strength, ductility, and toughness, which are vital for predicting performance and ensuring structural integrity in countless applications.\n\n## Your Questions Answered\n\n### What is Stress?\n\n**Stress** is a measure of the internal forces acting within a deformable body. When an external force is applied to an object, it creates internal resisting forces within the material's cross-section. Stress quantifies the intensity of these internal forces distributed over a given area. It is typically calculated by dividing the applied force by the cross-sectional area over which it acts.\n\nMathematically, stress ($\\sigma$) is expressed as:\n$\\sigma = F/A$\nWhere:\n*   **F** is the applied force\n*   **A** is the cross-sectional area\n\nStress is usually measured in Pascals (Pa) or pounds per square inch (psi). There are different types of stress, including **tensile stress** (pulling apart), **compressive stress** (pushing together), and **shear stress** (forces parallel to the surface, causing twisting or sliding).\n\n### What is Strain?\n\n**Strain** is a measure of the deformation of a material in response to an applied stress. Unlike stress, which describes the internal forces, strain describes the geometric changes in the material, specifically the relative change in shape or size. It is a dimensionless quantity, often expressed as a percentage or a simple ratio, as it represents a change in length divided by the original length.\n\nMathematically, strain ($\\epsilon$) is expressed as:\n$\\epsilon = \\Delta L / L_0$\nWhere:\n*   **$\\Delta L$** is the change in length (deformation)\n*   **$L_0$** is the original length\n\nSimilar to stress, there are different types of strain: **tensile strain** (elongation), **compressive strain** (shortening), and **shear strain** (angular deformation). Strain provides insight into how much a material stretches or compresses under load, indicating its ductility or brittleness.\n\n### Why is the Stress-Strain Graph Important?\n\nThe stress-strain graph is indispensable in engineering and materials science because it provides a comprehensive fingerprint of a material's mechanical behavior. It allows engineers to:\n\n*   **Characterize Materials:** Determine fundamental properties such as stiffness, strength, ductility, and toughness.\n*   **Predict Performance:** Understand how a material will respond under various loading conditions, from slight bending to extreme impacts.\n*   **Ensure Safety:** Identify the limits of a material's integrity, such as its yield strength (where permanent deformation begins) and ultimate tensile strength (maximum load it can bear). This is critical for designing safe structures and components.\n*   **Select Appropriate Materials:** Compare different materials to choose the most suitable one for a specific application, considering factors like cost, weight, and environmental conditions.\n*   **Optimize Design:** Refine component geometries and sizes to minimize material usage while maintaining required strength and durability.\n\nWithout this graph, predicting material behavior would be largely guesswork, leading to inefficient designs, material failures, and potentially catastrophic consequences.\n\n### How is a Stress-Strain Graph Generated?\n\nA stress-strain graph is typically generated through a standardized mechanical test, most commonly the **tensile test**. In this experiment, a precisely machined specimen of the material (often a \"dog-bone\" shape to ensure fracture occurs in the gauge section) is mounted into a universal testing machine.\n\nThe process involves:\n1.  **Gripping the Specimen:** The ends of the specimen are securely clamped in the machine's grips.\n2.  **Applying a Load:** A controlled tensile (pulling) force is gradually applied to the specimen, causing it to elongate.\n3.  **Measuring Force and Deformation:** The testing machine continuously measures the applied load (force) and the corresponding elongation (change in length) of the specimen. An extensometer is often used to precisely measure the elongation within a defined gauge length.\n4.  **Calculating Stress and Strain:** The measured force is divided by the original cross-sectional area of the specimen to calculate **engineering stress**. The measured elongation is divided by the original gauge length to calculate **engineering strain**.\n5.  **Plotting the Data:** These calculated stress and strain values are then plotted against each other, with stress on the y-axis and strain on the x-axis, to produce the stress-strain graph. The test continues until the specimen fractures.\n\nThis systematic process ensures consistent and repeatable results, allowing for accurate comparison and characterization of different materials.\n\n### What are the Key Regions and Points on a Stress-Strain Graph?\n\nThe stress-strain graph reveals several critical regions and points that define a material's mechanical properties:\n\n*   **Elastic Region (Linear-Elastic Region):** This initial portion of the curve represents reversible deformation. If the load is removed within this region, the material will return to its original shape. For many materials, this region is linear, following **Hooke's Law**, which states that stress is directly proportional to strain ($\\sigma = E\\epsilon$).\n    *   **Proportional Limit:** The point where the linear relationship between stress and strain ends.\n    *   **Elastic Limit:** The maximum stress a material can withstand without undergoing permanent deformation. Often very close to the proportional limit.\n    *   **Modulus of Elasticity (Young's Modulus, E):** The slope of the linear-elastic region. It quantifies the material's stiffness or resistance to elastic deformation. A higher modulus indicates a stiffer material.\n*   **Yield Point (or Yield Strength):** This is arguably one of the most critical points. It represents the stress at which a material begins to deform permanently (plastically). For materials with a distinct yield point (like many steels), there's a clear drop or plateau in stress. For others, an offset yield strength (e.g., 0.2% offset yield strength) is determined by drawing a line parallel to the elastic region from a specified strain offset.\n*   **Plastic Region:** Beyond the yield point, the material undergoes permanent, irreversible deformation. Even if the load is removed, the material will not fully return to its original dimensions. In this region, the material often exhibits **strain hardening**, where its resistance to further deformation increases.\n*   **Ultimate Tensile Strength (UTS):** This is the maximum stress the material can withstand before it begins to neck (localize deformation) and eventually fracture. It represents the peak stress on the stress-strain curve.\n*   **Fracture Point (or Breaking Strength):** The point at which the material ruptures or breaks. The stress at this point may be lower than the UTS due to the reduction in cross-sectional area during necking.\n*   **Ductility:** A measure of a material's ability to undergo plastic deformation before fracture. It is often quantified by the **percent elongation** (the percentage increase in length at fracture) or **percent reduction in area**. Materials with a large plastic region are considered",
  "format": "FAQ Style",
  "word_count": 1432,
  "products_mentioned": [
    "PrimeBiome",
    "Java Burn"
  ],
  "generated_at": "2025-10-15T21:52:42.821404"
}