{
  "keyword": "supplements vegans should take",
  "title": "Supplements Vegans Should Take",
  "content": "## 1. Introduction to Vegan Supplements\n*Disclosure: This article contains affiliate links. If you choose to purchase through these links, we may earn a commission at no additional cost to you. This helps us continue providing free health information.*\nAs the world becomes more health-conscious, many individuals are turning to a vegan lifestyle for its numerous benefits. However, a well-planned vegan diet can sometimes be challenging, and supplements can play a crucial role in filling nutritional gaps. In this article, we will explore the benefits and tips for supplements vegans should take to ensure they are getting all the necessary nutrients for optimal health.\n\n## 2. Understanding the Science Behind Vegan Supplements\nA vegan diet excludes all animal products, including meat, dairy, and eggs. While a vegan diet can be rich in nutrients, it may be low in certain vitamins and minerals that are predominantly found in animal products. For instance, vitamin B12, which is essential for brain function and blood formation, is primarily found in animal products. Therefore, vegans may need to rely on supplements to meet their daily nutritional needs.\n\n## 3. 10 Benefits of Supplements for Vegans\nHere are the top benefits of supplements for vegans:\n1. **Improved heart health**: Omega-3 fatty acid supplements, particularly alpha-linolenic acid (ALA), can help reduce inflammation and improve heart health.\n2. **Increased energy levels**: Iron supplements can help combat fatigue and increase energy levels, which is especially important for vegans who may be at risk of iron deficiency.\n3. **Stronger bones**: Calcium and vitamin D supplements can help maintain strong bones and prevent conditions like osteoporosis.\n4. **Healthy brain function**: Many people find that brain health supplements can be helpful. [Click here](https://a851ey-huapohuajrpvm2bj0lq.hop.clickbank.net) to learn more about NeuroQuiet, which brain health and tinnitus relief supplement.\n5. **Reduced risk of chronic diseases**: Antioxidant supplements, such as vitamin C and E, can help protect against chronic diseases like cancer and diabetes.\n6. **Improved digestion**: Probiotic supplements can help maintain a healthy gut microbiome, which is essential for proper digestion and immune function.\n7. **Healthy skin, hair, and nails**: Vitamin B supplements, particularly biotin, can help maintain healthy skin, hair, and nails.\n8. **Supports immune function**: Zinc supplements can help support immune function and reduce the risk of illnesses like the common cold.\n9. **May improve mood**: Vitamin D supplements have been shown to have a positive effect on mood and may help reduce symptoms of depression.\n10. **Supports eye health**: Lutein and zeaxanthin supplements can help protect the eyes against damage and reduce the risk of age-related macular degeneration.\n\n## 4. Practical Tips for Taking Supplements as a Vegan\nWhile supplements can be beneficial, it is essential to follow some practical tips to ensure you are getting the most out of them:\n- Always consult with a healthcare provider before taking any supplements to determine the best course of treatment for your individual needs.\n- Choose high-quality supplements from reputable manufacturers to ensure purity and potency.\n- Follow the recommended dosage instructions to avoid overdose or interactions with other medications.\n- Monitor your body's response to supplements and adjust your regimen as needed.\n- Maintain a balanced diet and lifestyle to get the most out of your supplements.\n\n## 5. Conclusion\nIn conclusion, supplements can play a vital role in maintaining optimal health for vegans. By understanding the science behind vegan supplements and incorporating the benefits and tips outlined in this article, individuals can ensure they are getting all the necessary nutrients for a healthy and balanced lifestyle. If you're looking for additional support, consider exploring [click here](https://a851ey-huapohuajrpvm2bj0lq.hop.clickbank.net) to learn more about NeuroQuiet. Remember to always consult with a healthcare provider before taking any supplements, and prioritize a balanced diet and lifestyle for optimal health.",
  "format": "Benefits & Tips",
  "word_count": 621,
  "products_mentioned": [
    "NeuroQuiet"
  ],
  "generated_at": "2025-10-18T17:06:48.199480",
  "api_used": "fireworks",
  "version": "v2_12_formats"
}